ctat/__init__.py
ctat/__main__.py
ctat/cell_type_annotation.py
ctat/file_utils.py
ctat/schema_validator.py
ctat/tabular_serializer.py
schema/ctat_schema.yaml
ctat-0.0.1.dist-info/LICENSE
ctat-0.0.1.dist-info/METADATA
ctat-0.0.1.dist-info/WHEEL
ctat-0.0.1.dist-info/entry_points.txt
ctat-0.0.1.dist-info/top_level.txt
ctat-0.0.1.dist-info/RECORD
