Metadata-Version: 2.1
Name: ctat
Version: 0.0.1
Summary: The aim of this project is to specify the Cell Type Annotation schema and related data standardization operations.
Home-page: https://github.com/hkir-dev/cell-type-annotation-tools
Author: 
License: Apache-2.0 license
Platform: UNKNOWN
Classifier: Programming Language :: Python :: 3
Classifier: License :: OSI Approved :: GNU General Public License v3 (GPLv3)
Classifier: Operating System :: OS Independent
Requires-Dist: jsonschema
Requires-Dist: ruamel.yaml
Requires-Dist: dataclasses-json
Requires-Dist: pandas
